scrapy_item_pipelines/__init__.py
scrapy_item_pipelines/misc.py
scrapy_item_pipelines/streaming.py
scrapy_item_pipelines-0.2.dist-info/LICENSE
scrapy_item_pipelines-0.2.dist-info/WHEEL
scrapy_item_pipelines-0.2.dist-info/METADATA
scrapy_item_pipelines-0.2.dist-info/RECORD
