Metadata-Version: 2.1
Name: scrapy-item-pipelines
Version: 0.2
Summary: Collection of reusable scrapy item pipelines
Home-page: https://github.com/singletonlabs/scrapy-item-pipelines
Keywords: scrapy,pipelines
Author: Kasun Herath
Author-email: kasunh01@gmail.com
Requires-Python: >=3.6
Classifier: Intended Audience :: Developers
Classifier: License :: OSI Approved :: MIT License
Classifier: Framework :: Scrapy
Classifier: Programming Language :: Python
Classifier: Programming Language :: Python :: 3
Classifier: Programming Language :: Python :: 3.6
Classifier: Programming Language :: Python :: Implementation :: CPython
Requires-Dist: confluent-kafka
Requires-Dist: flake8 ; extra == "dev"
Provides-Extra: dev
